{
  "args": {
    "backbone": "convnext_tiny",
    "train_csv": "artifacts/csvs/cv2024_training_dedup_le6.csv",
    "orig_val_csv": "<CV2024_ROOT>/validation/validation_data.xlsx",
    "dedup_val_csv": "artifacts/csvs/cv2024_validation_dedup_le6.csv",
    "seeds": [
      9
    ],
    "epochs": 10,
    "batch": 128,
    "output": "crossmodel/convnext_shards/phase5_crossmodel_convnextT_le6_s9.json"
  },
  "meta": {
    "description": "Frozen-backbone robustness diagnostic; reports final-epoch balanced accuracy, not an official CV2024 leaderboard metric.",
    "script_path": "<CAPSULE_ARTIFACT_ROOT>/src/counterfactual/03_cross_model.py",
    "script_sha256": "8e129f22acff524315a195220214e660d82a98a53f2126265f382107701f6fc9",
    "script_version": "cross-model-v2-provenance",
    "torch_version": "2.6.0+cu124",
    "torchvision_version": null,
    "cuda_version": "12.4",
    "cudnn_version": 90100,
    "gpu_name": "NVIDIA L40S",
    "timestamp_start": "2026-04-29T20:39:50Z",
    "determinism_enabled": true,
    "input_files": {
      "train_csv": {
        "path": "<CAPSULE_ARTIFACT_ROOT>/artifacts/csvs/cv2024_training_dedup_le6.csv",
        "sha256": "9b17a218c183fd69590e26d79165ddd77671651e5d9641542211d9a1c8628c58"
      },
      "orig_val_csv": {
        "path": "<CV2024_ROOT>/validation/validation_data.xlsx",
        "sha256": "de88d19a43a0d30951678f763122622e562412c19911e6156effd77b5a6d4de1"
      },
      "dedup_val_csv": {
        "path": "<CAPSULE_ARTIFACT_ROOT>/artifacts/csvs/cv2024_validation_dedup_le6.csv",
        "sha256": "0e1ca377c29b4723d3fbb217f3865c74e55ed67d38353d4f7782cfe40d6eaf5c"
      }
    },
    "timestamp_end": "2026-04-29T20:51:53Z"
  },
  "runs": [
    {
      "seed": 9,
      "backbone": "convnext_tiny",
      "history": [
        {
          "epoch": 1,
          "loss": 1.8466163873672485,
          "orig_val": {
            "acc": 0.2868832134887181,
            "bal_acc": 0.37430814133626444,
            "f1_macro": 0.2591749150559277,
            "null_acc": 0.7616538556905529,
            "n_test": 16132
          },
          "dedup_val": {
            "acc": 0.5497692814765985,
            "bal_acc": 0.48518716550380336,
            "f1_macro": 0.45246991931464053,
            "null_acc": 0.4361678751922654,
            "n_test": 4551
          },
          "kvasir_s1": {
            "acc": 0.20134789452971272,
            "bal_acc": 0.2256201017615163,
            "f1_macro": 0.11352229248048447,
            "null_acc": 0.9093368752459662,
            "n_test": 20328
          },
          "train_s": 62.26980767585337
        },
        {
          "epoch": 2,
          "loss": 1.8332257270812988,
          "orig_val": {
            "acc": 0.22266303000247956,
            "bal_acc": 0.40651710830477567,
            "f1_macro": 0.26790784739825574,
            "null_acc": 0.7616538556905529,
            "n_test": 16132
          },
          "dedup_val": {
            "acc": 0.5710832784003516,
            "bal_acc": 0.5305302934993061,
            "f1_macro": 0.4638763790711461,
            "null_acc": 0.4361678751922654,
            "n_test": 4551
          },
          "kvasir_s1": {
            "acc": 0.09322117276662731,
            "bal_acc": 0.22706569671429722,
            "f1_macro": 0.08547881107051779,
            "null_acc": 0.9093368752459662,
            "n_test": 20328
          },
          "train_s": 61.650917364284396
        },
        {
          "epoch": 3,
          "loss": 1.6955475807189941,
          "orig_val": {
            "acc": 0.215472353087032,
            "bal_acc": 0.4099854716865107,
            "f1_macro": 0.2905123850353287,
            "null_acc": 0.7616538556905529,
            "n_test": 16132
          },
          "dedup_val": {
            "acc": 0.6007470885519666,
            "bal_acc": 0.5573226432863769,
            "f1_macro": 0.5082603034938711,
            "null_acc": 0.4361678751922654,
            "n_test": 4551
          },
          "kvasir_s1": {
            "acc": 0.07639708776072412,
            "bal_acc": 0.22162187872209188,
            "f1_macro": 0.08441748651332369,
            "null_acc": 0.9093368752459662,
            "n_test": 20328
          },
          "train_s": 62.87551287934184
        },
        {
          "epoch": 4,
          "loss": 1.6121182441711426,
          "orig_val": {
            "acc": 0.21900570295065708,
            "bal_acc": 0.4382039677643984,
            "f1_macro": 0.29524035384940495,
            "null_acc": 0.7616538556905529,
            "n_test": 16132
          },
          "dedup_val": {
            "acc": 0.6022852120413096,
            "bal_acc": 0.5809718164299578,
            "f1_macro": 0.5198182931993758,
            "null_acc": 0.4361678751922654,
            "n_test": 4551
          },
          "kvasir_s1": {
            "acc": 0.07797127115308934,
            "bal_acc": 0.22921203222367406,
            "f1_macro": 0.09206096561172764,
            "null_acc": 0.9093368752459662,
            "n_test": 20328
          },
          "train_s": 63.84473956376314
        },
        {
          "epoch": 5,
          "loss": 1.5390863418579102,
          "orig_val": {
            "acc": 0.21640218199851227,
            "bal_acc": 0.4336368239976597,
            "f1_macro": 0.3027964896492178,
            "null_acc": 0.7616538556905529,
            "n_test": 16132
          },
          "dedup_val": {
            "acc": 0.6156888595912986,
            "bal_acc": 0.5868331955302819,
            "f1_macro": 0.5426849289496789,
            "null_acc": 0.4361678751922654,
            "n_test": 4551
          },
          "kvasir_s1": {
            "acc": 0.07408500590318771,
            "bal_acc": 0.23344945547370127,
            "f1_macro": 0.08497364955024087,
            "null_acc": 0.9093368752459662,
            "n_test": 20328
          },
          "train_s": 64.85373339056969
        },
        {
          "epoch": 6,
          "loss": 1.6824064254760742,
          "orig_val": {
            "acc": 0.2320233077113811,
            "bal_acc": 0.42571615192451356,
            "f1_macro": 0.2999872194410295,
            "null_acc": 0.7616538556905529,
            "n_test": 16132
          },
          "dedup_val": {
            "acc": 0.6273346517248957,
            "bal_acc": 0.5731188557179936,
            "f1_macro": 0.5573936438386947,
            "null_acc": 0.4361678751922654,
            "n_test": 4551
          },
          "kvasir_s1": {
            "acc": 0.0878099173553719,
            "bal_acc": 0.23512521708377748,
            "f1_macro": 0.09567266457866853,
            "null_acc": 0.9093368752459662,
            "n_test": 20328
          },
          "train_s": 63.15123947896063
        },
        {
          "epoch": 7,
          "loss": 1.6158080101013184,
          "orig_val": {
            "acc": 0.22123729233820977,
            "bal_acc": 0.44215604753881255,
            "f1_macro": 0.30524900171494074,
            "null_acc": 0.7616538556905529,
            "n_test": 16132
          },
          "dedup_val": {
            "acc": 0.6203032300593276,
            "bal_acc": 0.6029039836756283,
            "f1_macro": 0.5483376495435751,
            "null_acc": 0.4361678751922654,
            "n_test": 4551
          },
          "kvasir_s1": {
            "acc": 0.07738095238095238,
            "bal_acc": 0.23260047018343474,
            "f1_macro": 0.08817104641534826,
            "null_acc": 0.9093368752459662,
            "n_test": 20328
          },
          "train_s": 61.56991186738014
        },
        {
          "epoch": 8,
          "loss": 1.4842448234558105,
          "orig_val": {
            "acc": 0.2214852467146045,
            "bal_acc": 0.44077502984581907,
            "f1_macro": 0.30780564290400325,
            "null_acc": 0.7616538556905529,
            "n_test": 16132
          },
          "dedup_val": {
            "acc": 0.6198637662052296,
            "bal_acc": 0.6027856378925592,
            "f1_macro": 0.5593384209300994,
            "null_acc": 0.4361678751922654,
            "n_test": 4551
          },
          "kvasir_s1": {
            "acc": 0.07767611176702086,
            "bal_acc": 0.23538861190149668,
            "f1_macro": 0.09407518140412602,
            "null_acc": 0.9093368752459662,
            "n_test": 20328
          },
          "train_s": 60.95803324133158
        },
        {
          "epoch": 9,
          "loss": 1.7514076232910156,
          "orig_val": {
            "acc": 0.2194396231093479,
            "bal_acc": 0.44007099774729735,
            "f1_macro": 0.3072050705342644,
            "null_acc": 0.7616538556905529,
            "n_test": 16132
          },
          "dedup_val": {
            "acc": 0.6233794770380137,
            "bal_acc": 0.5975806867900011,
            "f1_macro": 0.5575000224795715,
            "null_acc": 0.4361678751922654,
            "n_test": 4551
          },
          "kvasir_s1": {
            "acc": 0.07536402990948446,
            "bal_acc": 0.23417778818903617,
            "f1_macro": 0.09139029519541392,
            "null_acc": 0.9093368752459662,
            "n_test": 20328
          },
          "train_s": 62.686140367761254
        },
        {
          "epoch": 10,
          "loss": 1.4352624416351318,
          "orig_val": {
            "acc": 0.21912968013885445,
            "bal_acc": 0.4399432021188572,
            "f1_macro": 0.3066826250886775,
            "null_acc": 0.7616538556905529,
            "n_test": 16132
          },
          "dedup_val": {
            "acc": 0.6229400131839157,
            "bal_acc": 0.5982600711358071,
            "f1_macro": 0.5577370882635283,
            "null_acc": 0.4361678751922654,
            "n_test": 4551
          },
          "kvasir_s1": {
            "acc": 0.07521645021645022,
            "bal_acc": 0.23415750147007486,
            "f1_macro": 0.09124496425993318,
            "null_acc": 0.9093368752459662,
            "n_test": 20328
          },
          "train_s": 62.97028933092952
        }
      ],
      "last": {
        "epoch": 10,
        "loss": 1.4352624416351318,
        "orig_val": {
          "acc": 0.21912968013885445,
          "bal_acc": 0.4399432021188572,
          "f1_macro": 0.3066826250886775,
          "null_acc": 0.7616538556905529,
          "n_test": 16132
        },
        "dedup_val": {
          "acc": 0.6229400131839157,
          "bal_acc": 0.5982600711358071,
          "f1_macro": 0.5577370882635283,
          "null_acc": 0.4361678751922654,
          "n_test": 4551
        },
        "kvasir_s1": {
          "acc": 0.07521645021645022,
          "bal_acc": 0.23415750147007486,
          "f1_macro": 0.09124496425993318,
          "null_acc": 0.9093368752459662,
          "n_test": 20328
        },
        "train_s": 62.97028933092952
      }
    }
  ]
}